moviecolor/__init__.py
moviecolor/__main__.py
moviecolor/core.py
moviecolor/ffmpeg_utils.py
moviecolor-2.0.0.dist-info/licenses/LICENSE.md
moviecolor-2.0.0.dist-info/METADATA
moviecolor-2.0.0.dist-info/WHEEL
moviecolor-2.0.0.dist-info/entry_points.txt
moviecolor-2.0.0.dist-info/top_level.txt
moviecolor-2.0.0.dist-info/RECORD
