Metadata-Version: 2.4
Name: moviecolor
Version: 2.0.0
Summary: Generate a 'Moviebarcode' of a video using ffmpeg with real-time progress interface.
Home-page: https://github.com/AsaadMe/MovieColor
Download-URL: https://github.com/AsaadMe/MovieColor/releases/tag/v1.2.1
Author: Mehran Asaad
Author-email: Mehran Asaad <mehran.asaad@gmail.com>
License-Expression: MIT
Project-URL: Repository, https://github.com/AsaadMe/MovieColor
Keywords: moviebarcode,movie,barcode
Classifier: Programming Language :: Python :: 3
Classifier: Operating System :: OS Independent
Requires-Python: >=3.8
License-File: LICENSE.md
Requires-Dist: pillow>=11.3.0
Dynamic: author
Dynamic: download-url
Dynamic: home-page
Dynamic: license-file
Dynamic: requires-python
